{"elements":[{"from":[7.179161,5.6165733,7.241542],"to":[9.464875,8.473717,9.527256],"rotation":{"angle":0.0,"axis":"y","origin":[8.607733,6.4737163,8.955828]},"faces":{"east":{"uv":[1.25,6.5,1.75,7.125],"rotation":0,"texture":"#0","tintindex":0},"south":{"uv":[1.875,6.5,2.375,7.125],"rotation":0,"texture":"#0","tintindex":0},"north":{"uv":[0.625,6.5,1.125,7.125],"rotation":0,"texture":"#0","tintindex":0},"west":{"uv":[6.5,2.25,7.0,2.875],"rotation":0,"texture":"#0","tintindex":0},"up":{"uv":[0.5,7.625,0.0,7.125],"rotation":0,"texture":"#0","tintindex":0},"down":{"uv":[7.625,2.25,7.125,2.75],"rotation":0,"texture":"#0","tintindex":0}}}],"textures":{"0":"modelengine:entity/nocsy_mount_lizard_baby"},"display":{"head":{"translation":[0.0,-6.4,0.0],"scale":[4.0,4.0,4.0]}}}