{"elements":[{"from":[-0.57142925,8.0,4.8571424],"to":[8.571428,8.0,12.857143],"rotation":{"angle":0.0,"axis":"y","origin":[11.428572,2.5714283,11.142858]},"faces":{"east":{"uv":[7.125,4.0,8.875,4.0],"rotation":0,"texture":"#0","tintindex":0},"south":{"uv":[4.125,7.125,6.125,7.125],"rotation":0,"texture":"#0","tintindex":0},"north":{"uv":[7.125,3.875,9.125,3.875],"rotation":0,"texture":"#0","tintindex":0},"west":{"uv":[7.125,4.125,8.875,4.125],"rotation":0,"texture":"#0","tintindex":0},"up":{"uv":[4.125,1.75,2.125,0.0],"rotation":0,"texture":"#0","tintindex":0},"down":{"uv":[4.125,0.0,2.125,1.75],"rotation":0,"texture":"#0","tintindex":0}}}],"textures":{"0":"modelengine:entity/nocsy_mount_moth_baby"},"display":{"head":{"translation":[0.0,-6.4,0.0],"scale":[4.0,4.0,4.0]}}}